{
  "kind": "collectionType",
  "collectionName": "topics",
  "info": {
    "singularName": "topic",
    "pluralName": "topics",
    "displayName": "Topic"
  },
  "options": {
    "draftAndPublish": true
  },
  "pluginOptions": {},
  "attributes": {
    "title": {
      "type": "string"
    },
    "text": {
      "type": "richtext"
    },
    "typeOfTopic": {
      "type": "enumeration",
      "enum": [
        "aktuellesThema",
        "allgemeinesThema"
      ],
      "required": true
    },
    "images": {
      "allowedTypes": [
        "images",
        "files",
        "videos"
      ],
      "type": "media",
      "multiple": true
    },
    "subTitle": {
      "type": "string"
    }
  }
}
